the_true/__init__.py
the_true/the_true.py
the_true-0.0.5.dist-info/LICENSE
the_true-0.0.5.dist-info/METADATA
the_true-0.0.5.dist-info/WHEEL
the_true-0.0.5.dist-info/top_level.txt
the_true-0.0.5.dist-info/RECORD
